neurospatial/__init__.py
neurospatial/_constants.py
neurospatial/_logging.py
neurospatial/alignment.py
neurospatial/calibration.py
neurospatial/composite.py
neurospatial/distance.py
neurospatial/environment.py
neurospatial/field_ops.py
neurospatial/io.py
neurospatial/kernels.py
neurospatial/py.typed
neurospatial/spatial.py
neurospatial/transforms.py
neurospatial/layout/__init__.py
neurospatial/layout/base.py
neurospatial/layout/factories.py
neurospatial/layout/mixins.py
neurospatial/layout/validation.py
neurospatial/layout/engines/__init__.py
neurospatial/layout/engines/graph.py
neurospatial/layout/engines/hexagonal.py
neurospatial/layout/engines/image_mask.py
neurospatial/layout/engines/masked_grid.py
neurospatial/layout/engines/regular_grid.py
neurospatial/layout/engines/shapely_polygon.py
neurospatial/layout/engines/triangular_mesh.py
neurospatial/layout/helpers/__init__.py
neurospatial/layout/helpers/graph.py
neurospatial/layout/helpers/hexagonal.py
neurospatial/layout/helpers/regular_grid.py
neurospatial/layout/helpers/triangular_mesh.py
neurospatial/layout/helpers/utils.py
neurospatial/regions/__init__.py
neurospatial/regions/core.py
neurospatial/regions/io.py
neurospatial/regions/ops.py
neurospatial/regions/plot.py
neurospatial-0.2.0.dist-info/METADATA
neurospatial-0.2.0.dist-info/WHEEL
neurospatial-0.2.0.dist-info/licenses/LICENSE
neurospatial-0.2.0.dist-info/RECORD
