Metadata-Version: 2.4
Name: neurospatial
Version: 0.2.0
Summary: Discretize continuous N-dimensional spatial environments into bins/nodes with connectivity graphs
Project-URL: Homepage, https://github.com/edeno/neurospatial
Project-URL: Repository, https://github.com/edeno/neurospatial
Project-URL: Issues, https://github.com/edeno/neurospatial/issues
Author-email: Eric Denovellis <eric.denovellis@ucsf.edu>
License: MIT
License-File: LICENSE
Keywords: discretization,navigation,neuroscience,place-fields,spatial
Classifier: Development Status :: 3 - Alpha
Classifier: Intended Audience :: Science/Research
Classifier: License :: OSI Approved :: MIT License
Classifier: Operating System :: OS Independent
Classifier: Programming Language :: Python :: 3
Classifier: Programming Language :: Python :: 3.10
Classifier: Programming Language :: Python :: 3.11
Classifier: Programming Language :: Python :: 3.12
Classifier: Programming Language :: Python :: 3.13
Classifier: Topic :: Scientific/Engineering
Classifier: Topic :: Scientific/Engineering :: Bio-Informatics
Classifier: Topic :: Scientific/Engineering :: Information Analysis
Classifier: Typing :: Typed
Requires-Python: >=3.10
Requires-Dist: ipykernel>=6.0.0
Requires-Dist: jupyter>=1.1.1
Requires-Dist: matplotlib>=3.7.0
Requires-Dist: nbconvert>=7.16.6
Requires-Dist: networkx>=3.0
Requires-Dist: numpy>=1.24.0
Requires-Dist: pandas>=2.0.0
Requires-Dist: scikit-learn>=1.2.0
Requires-Dist: scipy>=1.10.0
Requires-Dist: shapely>=2.0.0
Requires-Dist: track-linearization>=2.4.0
Provides-Extra: dev
Requires-Dist: ipython>=8.0.0; extra == 'dev'
Requires-Dist: mypy>=1.18.2; extra == 'dev'
Requires-Dist: pre-commit>=4.3.0; extra == 'dev'
Requires-Dist: pytest-cov>=7.0.0; extra == 'dev'
Requires-Dist: pytest>=8.4.2; extra == 'dev'
Requires-Dist: ruff>=0.14.3; extra == 'dev'
Provides-Extra: docs
Requires-Dist: jupytext>=1.16.0; extra == 'docs'
Requires-Dist: mkdocs-gen-files>=0.5.0; extra == 'docs'
Requires-Dist: mkdocs-jupyter>=0.25.0; extra == 'docs'
Requires-Dist: mkdocs-literate-nav>=0.6.0; extra == 'docs'
Requires-Dist: mkdocs-material>=9.5.0; extra == 'docs'
Requires-Dist: mkdocs-section-index>=0.3.0; extra == 'docs'
Requires-Dist: mkdocs>=1.6.0; extra == 'docs'
Requires-Dist: mkdocstrings[python]>=0.26.0; extra == 'docs'
Provides-Extra: opencv
Requires-Dist: opencv-python>=4.11.0.86; extra == 'opencv'
